flask_urlsigning
