Metadata-Version: 1.1
Name: Flask-URLSigning
Version: 1.0.2
Summary: A flask extension to sign and verify signed urls.
Home-page: https://gitlab.com/prodrigues1990/flask-urlsigning
Author: Pedro Rodrigues
Author-email: prodrigues1990@gmail.com
License: GPLv2
Platform: any
Classifier: Environment :: Web Environment
Classifier: Intended Audience :: Developers
Classifier: License :: OSI Approved :: BSD License
Classifier: Operating System :: OS Independent
Classifier: Programming Language :: Python
Classifier: Topic :: Internet :: WWW/HTTP :: Dynamic Content
Classifier: Topic :: Software Development :: Libraries :: Python Modules
